moe_infinity/__init__.py
moe_infinity/distributed/__init__.py
moe_infinity/distributed/devicemap_manager.py
moe_infinity/distributed/expert_executor.py
moe_infinity/distributed/expert_prefetcher.py
moe_infinity/entrypoints/__init__.py
moe_infinity/entrypoints/big_modeling.py
moe_infinity/memory/__init__.py
moe_infinity/memory/expert_cache.py
moe_infinity/memory/expert_entry.py
moe_infinity/memory/expert_predictor.py
moe_infinity/memory/expert_prefetcher.py
moe_infinity/memory/expert_priority_score.py
moe_infinity/memory/expert_tracer.py
moe_infinity/modeling_grok/__init__.py
moe_infinity/modeling_grok/configuration_grok1.py
moe_infinity/modeling_grok/modeling_grok1.py
moe_infinity/modeling_grok/modeling_grok1_outputs.py
moe_infinity/models/__init__.py
moe_infinity/models/grok.py
moe_infinity/models/mixtral.py
moe_infinity/models/nllb_moe.py
moe_infinity/models/switch_transformers.py
moe_infinity/ops/__init__.py
moe_infinity/ops/core/aio/archer_aio_thread.cpp
moe_infinity/ops/core/aio/archer_aio_thread.h
moe_infinity/ops/core/aio/archer_aio_threadpool.cpp
moe_infinity/ops/core/aio/archer_aio_threadpool.h
moe_infinity/ops/core/aio/archer_aio_utils.cpp
moe_infinity/ops/core/aio/archer_aio_utils.h
moe_infinity/ops/core/aio/archer_prio_aio_handle.cpp
moe_infinity/ops/core/aio/archer_prio_aio_handle.h
moe_infinity/ops/core/aio/archer_tensor_handle.cpp
moe_infinity/ops/core/aio/archer_tensor_handle.h
moe_infinity/ops/core/aio/archer_tensor_index.cpp
moe_infinity/ops/core/aio/archer_tensor_index.h
moe_infinity/ops/core/common/pytorch.h
moe_infinity/ops/core/common/status.h
moe_infinity/ops/core/common/time.h
moe_infinity/ops/core/common/types.h
moe_infinity/ops/core/memory/host_caching_allocator.cpp
moe_infinity/ops/core/memory/host_caching_allocator.h
moe_infinity/ops/core/memory/memory_pool.cpp
moe_infinity/ops/core/memory/memory_pool.h
moe_infinity/ops/core/memory/stream_pool.cpp
moe_infinity/ops/core/memory/stream_pool.h
moe_infinity/ops/core/model/model_topology.cpp
test_proj_8e00a834c8-0.0.2.dist-info/LICENSE
test_proj_8e00a834c8-0.0.2.dist-info/METADATA
test_proj_8e00a834c8-0.0.2.dist-info/WHEEL
test_proj_8e00a834c8-0.0.2.dist-info/top_level.txt
test_proj_8e00a834c8-0.0.2.dist-info/RECORD
