Metadata-Version: 2.1
Name: test_proj_8e00a834c8
Version: 0.0.2
Home-page: https://github.com/TorchMoE/MoE-Infinity
Author: TorchMoE Team
License: Apache License 2.0
Project-URL: Homepage, https://github.com/TorchMoE/MoE-Infinity
Classifier: Programming Language :: Python :: 3.8
Classifier: Programming Language :: Python :: 3.9
Classifier: Programming Language :: Python :: 3.10
Classifier: Programming Language :: Python :: 3.11
Classifier: License :: OSI Approved :: Apache Software License
Classifier: Topic :: Scientific/Engineering :: Artificial Intelligence
Requires-Python: >=3.8
License-File: LICENSE
Requires-Dist: hjson
Requires-Dist: ninja
Requires-Dist: packaging >=20.0
Requires-Dist: py-cpuinfo
Requires-Dist: torch >=2.1.1
Requires-Dist: transformers <5.0.0,>=4.37.1
Requires-Dist: sentencepiece
Requires-Dist: pydantic ==1.10.12
Requires-Dist: datasets >=2.12.0
Requires-Dist: pyarrow ==12.0.0
Requires-Dist: accelerate
Requires-Dist: sphinx
Requires-Dist: scipy
Requires-Dist: chardet
Requires-Dist: optimum >=1.17.1
Requires-Dist: auto-gptq
